[
  {
      "id": 39,
      "name": "تست زیرمجموعه",
      "parentId": 38,
      "parentName": "testimage2",
      "active": true,
      "images": "default.jpg"
  },
  {
      "id": 38,
      "name": "testimage2",
      "parentId": 0,
      "parentName": null,
      "active": true,
      "images": "/images/00c3bc19-0f4a-4103-9ecb-439e5f66c390.jpg"
  },
  {
      "id": 37,
      "name": "car2",
      "parentId": 0,
      "parentName": null,
      "active": true,
      "images": "/images/dc91c2c7-6a28-4aa4-a6f2-5440c34aff06.jpg"
  },
  {
      "id": 36,
      "name": "string",
      "parentId": 0,
      "parentName": null,
      "active": true,
      "images": "رشته Base64 نامعتبر برای تصویر"
  },
  {
      "id": 33,
      "name": "hjghjghj",
      "parentId": 0,
      "parentName": null,
      "active": true,
      "images": "/images/7160784e-6121-4c40-b161-43cfd99632c9.jpg"
  },
  {
      "id": 32,
      "name": "hhhh",
      "parentId": 0,
      "parentName": null,
      "active": true,
      "images": "/images/e16f0d0b-1216-4f58-a62d-42d6b04be590.jpg"
  },
  {
      "id": 28,
      "name": "تست ۱۵۶۸",
      "parentId": null,
      "parentName": null,
      "active": true,
      "images": null
  },
  {
      "id": 27,
      "name": "تست ۶ عصر",
      "parentId": null,
      "parentName": null,
      "active": true,
      "images": null
  },
  {
      "id": 25,
      "name": "تست ۲۵",
      "parentId": null,
      "parentName": null,
      "active": true,
      "images": null
  },
  {
      "id": 24,
      "name": "تست ۲۴",
      "parentId": null,
      "parentName": null,
      "active": true,
      "images": null
  }
]