[
    {
        "id": 23,
        "operatorId": 1,
        "operator": {
            "id": 1,
            "name": "ایرانسل ",
            "active": true,
            "digit": 9,
            "createDate": "2023-12-26T14:36:57.4271492",
            "updateDate": "2024-01-04T14:54:49.2381576",
            "createDateEndSearch": null,
            "updateDateEndSearch": null,
            "userId": 0,
            "userName": null,
            "userIdUpdate": null,
            "userNameUpdate": null
        },
        "serial": 100,
        "sorceNumberId": null,
        "sorceNumber": null,
        "price": 15000,
        "status": 0,
        "createDate": "2024-01-05T15:24:26.1252329",
        "updateDate": null,
        "createDateEndSearch": null,
        "updateDateEndSearch": null,
        "userId": 0,
        "userName": null,
        "userIdUpdate": null,
        "userNameUpdate": null
    }
]